<?xml version="1.0" standalone="no" ?><manifest identifier="com.scorm.elucidat.build.58a42f9b85704_1487155261" version="1"
    xmlns="http://www.imsproject.org/xsd/imscp_rootv1p1p2"
    xmlns:adlcp="http://www.adlnet.org/xsd/adlcp_rootv1p2"
    xmlns:xsi="http://www.w3.org/2001/XMLSchema-instance"
    xsi:schemaLocation="http://www.imsproject.org/xsd/imscp_rootv1p1p2 imscp_rootv1p1p2.xsd
                       http://www.imsglobal.org/xsd/imsmd_rootv1p2p1 imsmd_rootv1p2p1.xsd
                       http://www.adlnet.org/xsd/adlcp_rootv1p2 adlcp_rootv1p2.xsd">
  <metadata>
    <schema>ADL SCORM</schema>
    <schemaversion>1.2</schemaversion>
  </metadata>
  <!-- There is just one organization. The organization contains just one item.-->
	<organizations default="elucidat_58a42f9b85704_1487155261">
		<organization identifier="elucidat_58a42f9b85704_1487155261">
			<title>SAI DACH: Global Data Protection</title>
			<item identifier="item_58a42f9b85704_1487155261" identifierref="resource_58a42f9b85704_1487155261">
				<title>SAI DACH: Global Data Protection</title>
				<adlcp:masteryscore>80</adlcp:masteryscore>
			</item>
		</organization>
	</organizations>
	<resources>
		<resource identifier="resource_58a42f9b85704_1487155261" type="webcontent" adlcp:scormtype="sco" href="launch.html">
			<file href="pages/5888d6b2bbfc9.js"/>
			<file href="pages/5888d6b1bcac6.js"/>
			<file href="pages/5888d6b2dfd27.js"/>
			<file href="pages/5888d6b2312b2.js"/>
			<file href="pages/5888d6b1b7109.js"/>
			<file href="pages/5888d6b1ce42c.js"/>
			<file href="pages/5888d6b1a4c3a.js"/>
			<file href="pages/5888d6b254e6c.js"/>
			<file href="pages/5888d6b1e85de.js"/>
			<file href="pages/5888d6b213b7e.js"/>
			<file href="pages/5888d6b248ca9.js"/>
			<file href="pages/5888d6b22b64f.js"/>
			<file href="pages/5888d6b1991bf.js"/>
			<file href="pages/5888d6b200d25.js"/>
			<file href="pages/5888d6b237351.js"/>
			<file href="pages/5888d6b1c8716.js"/>
			<file href="pages/5888d6b29d429.js"/>
			<file href="pages/5888d6b3045a3.js"/>
			<file href="pages/5888d6b31c3fc.js"/>
			<file href="pages/5888d6b27923b.js"/>
			<file href="pages/5888d6b1d422a.js"/>
			<file href="pages/5888d6b28b28a.js"/>
			<file href="pages/5888d6b26116f.js"/>
			<file href="pages/5888d6b1dffed.js"/>
			<file href="pages/5888d6b2b5ee4.js"/>
			<file href="pages/5888d6b26c5b5.js"/>
			<file href="pages/5888d6b23d13f.js"/>
			<file href="pages/5888d6b266c33.js"/>
			<file href="pages/5888d6b2aa759.js"/>
			<file href="pages/5888d6b2d42c4.js"/>
			<file href="pages/5888d6b31096d.js"/>
			<file href="pages/5888d6b1831b0.js"/>
			<file href="pages/5888d6b2e593e.js"/>
			<file href="pages/5888d6b291a91.js"/>
			<file href="pages/5888d6b219b90.js"/>
			<file href="pages/5888d6b24e75c.js"/>
			<file href="pages/5888d6b188c84.js"/>
			<file href="pages/5888d6b316351.js"/>
			<file href="pages/5888d6b1ab09b.js"/>
			<file href="pages/5888d6b1936f8.js"/>
			<file href="pages/5888d6b242bb7.js"/>
			<file href="pages/5888d6b2ce5f1.js"/>
			<file href="pages/5888d6b30ac86.js"/>
			<file href="pages/5888d6b2b0263.js"/>
			<file href="pages/5888d6b2c27ca.js"/>
			<file href="pages/5888d6b27f17e.js"/>
			<file href="pages/5888d6b18e034.js"/>
			<file href="pages/5888d6b2eba48.js"/>
			<file href="pages/5888d6b19e755.js"/>
			<file href="pages/5888d6b2c8a1b.js"/>
			<file href="pages/5888d6b25af9b.js"/>
			<file href="pages/5888d6b1c2d97.js"/>
			<file href="pages/5888d6b2976fc.js"/>
			<file href="pages/5888d6b1b1120.js"/>
			<file href="pages/5888d6b20d9cd.js"/>
			<file href="pages/5888d6b225ac5.js"/>
			<file href="pages/5888d6b272eff.js"/>
			<file href="pages/5888d6b1d9d8a.js"/>
			<file href="pages/5888d6b2a3a0a.js"/>
			<file href="pages/5888d6b21fb1e.js"/>
			<file href="pages/5888d6b2d9ea0.js"/>
			<file href="pages/5888d6b1ef237.js"/>
			<file href="pages/5888d6b20790f.js"/>
			<file href="pages/5888d6b2850f4.js"/>
			<file href="pages/5888d6b2f24c2.js"/>
			<file href="assets/5/a0cc2e58a7ad433fb5662eb7312f33e0.png"/>
			<file href="assets/5/96631e9ed73342884ac66f22b3c8efb8.jpg"/>
			<file href="assets/5/53c6989b4fa37c761e7d69a9daa80cd3.jpg"/>
			<file href="assets/5/c18b7487433b64d87ca279032c2e2a50.jpg"/>
			<file href="assets/5/067b8f7857d04733e0df313f959163c2.jpg"/>
			<file href="assets/5/28f938329487d9c24d12982e5596c355.png"/>
			<file href="assets/5/8a6df578531ed656771312c3024e37d7.png"/>
			<file href="assets/5/7fa495e7f913c88aca473f17c383dd5c.jpg"/>
			<file href="assets/5/6b75e8a522bc2bd26c41ac8a602a145c.png"/>
			<file href="assets/5/30aed75ccf5e1694a4d6fee07557bac8.png"/>
			<file href="assets/5/4428bdca1d26af0001367949b0e254ed.png"/>
			<file href="assets/5/14253109186060b15dbbae33ec55d2b5.png"/>
			<file href="assets/5/60b5e379aae63e24204b53a47afb81e3.png"/>
			<file href="assets/5/4995e62635553ec4b75add1be1ad4a6f.png"/>
			<file href="assets/5/dfc9e4f9d6880c421851b23761f2072a.png"/>
			<file href="assets/5/d5c21fff492762c207012c0abeca2cee.jpg"/>
			<file href="assets/5/6565b96bfdffcf092c00de2d298de0b9.jpg"/>
			<file href="assets/5/e30e7bfea4395ce0774d130e556cd979.png"/>
			<file href="assets/5/04a35cbe9a8157d5c519b29e148fd471.png"/>
			<file href="assets/5/c839a7ada165200d10dfd1816d42c356.png"/>
			<file href="assets/5/41f75c508565b151f31cd60f079b87bf.png"/>
			<file href="assets/5/18f1c0bc74338c17063830527646648b.jpg"/>
			<file href="assets/5/d2bbf042bf0ded50fce5aef152b7ba05.png"/>
			<file href="assets/5/6a0ee273bc3736a028c3bcbad275227e.png"/>
			<file href="assets/5/eff3d7d54ff50e26daa4793df11f4d72.png"/>
			<file href="assets/5/be9fd00dedb5a2e45f4c21866d7aaaf0.png"/>
			<file href="assets/5/443ae66ca36f895fbf06282808792c63.png"/>
			<file href="assets/5/265613b3311e59f6190f65b93e384d4e.png"/>
			<file href="assets/5/3bca40a9588e97c685dcd7a8726ef195.jpg"/>
			<file href="assets/5/9ceb67b64fa4b30a3b039596b4d21e90.jpg"/>
			<file href="assets/5/d03ba573e475f06af71d179fd3ce9b61.png"/>
			<file href="assets/5/ab2cbe4cc37fd3ed8e939e48cd90e729.png"/>
			<file href="assets/5/d479914c2f55394327d6fe8fbb089abf.png"/>
			<file href="assets/5/50f64a81fc70bdb5fe52aeca8f0f708b.png"/>
			<file href="assets/5/e84d57351238e53573581ca4963d32cf.png"/>
			<file href="assets/5/c604ceedb3100421d06fe39405a9ad2b.png"/>
			<file href="assets/5/9465b98401430b74f835a364737a0b07.png"/>
			<file href="assets/5/caeeacf520844e065e3e9afa15bebdc1.png"/>
			<file href="assets/5/e39c5eaa21f028b958518799db01bba9.png"/>
			<file href="assets/5/1bbd5ff4baccd6cd581f9ea8f58e8ddf.jpg"/>
			<file href="assets/5/937cab97eecef269bc0de1ec152aea54.jpg"/>
			<file href="assets/5/2f34c4555e8403276671466628d9ae62.jpg"/>
			<file href="assets/5/6f90ff77bdfc6fad6b3dece1bd5fe974.jpg"/>
			<file href="assets/5/5618b456de91b2672d2b360d81ce860e.png"/>
			<file href="assets/5/d890b19804c47f2ac5e798d13973d20b.jpg"/>
			<file href="assets/5/96c1428540d874c9a95cda14d8f1e10a.png"/>
			<file href="assets/5/74ebf88b49fc33c5cd8db97b8af0b7ee.png"/>
			<file href="assets/5/e04e916e8d91f0dd99a3f2ec4d68263d.png"/>
			<file href="assets/5/4a692eefb108c0758062d3a0d9b4c8b7.png"/>
			<file href="assets/5/aa51837744922fe774f105faabf99c8d.png"/>
			<file href="assets/5/02b8132cf76e4e2639d327f3590f4e71.png"/>
			<file href="assets/5/896b669fd4ba765ea7f0f8340fc4ca00.png"/>
			<file href="assets/5/06fde0b4cb5f98673802d6e23d5c924f.jpg"/>
			<file href="assets/4/58928ddb1bf7f29ad643ec064bfa7ddd.jpeg"/>
			<file href="assets/4/7c99b9892c3d239b01681e9e319fa0ef.png"/>
			<file href="assets/4/a1acc7e792df75dcd33748c94771b31a.jpeg"/>
			<file href="assets/8/4b464f6c0be906ceec07b578960e98c5.jpg"/>
			<file href="assets/8/6d4854ed823471e40a7bd40de1d5f577.jpg"/>
			<file href="assets/8/c15808169ec923ab88385eba27d7ca26.png"/>
			<file href="assets/8/40ffcff021084f2b8e66f7d5e78b7cd6.png"/>
			<file href="assets/8/fb4af0fa384e910b515d33c808d170a3.jpg"/>
			<file href="assets/8/641d04cdfc866d813970439ebbbc7915.png"/>
			<file href="assets/8/5db1bb06f7158d2e896f7752d2747c52.png"/>
			<file href="assets/8/16c18308358bee99f38666b726ec16f1.jpg"/>
			<file href="assets/8/8c982d5012ef1b8618f1151c90353319.jpg"/>
			<file href="assets/8/a9a60f43ca659ce73d020c093e4a65c4.png"/>
			<file href="assets/8/3e231e0a0b34961eb3066d6a67c852fc.jpg"/>
			<file href="assets/8/867457072a25c0d734b86f40ec608876.jpg"/>
			<file href="assets/8/b6f615af30ea984b12d88b6c50f9f96c.jpg"/>
			<file href="assets/8/418e16d6f5d2565ee1a63ce0b8725304.jpg"/>
			<file href="assets/8/4c6c1e22dcccf3e68d8551da27214fec.jpg"/>
			<file href="assets/8/a2dbe7a3cc1ca722bc92ae63590a36bc.png"/>
			<file href="assets/8/89484fd6e9e19c2d17e87d51493545e1.jpg"/>
			<file href="assets/8/1e005d2189614295282a47992a9032a1.jpg"/>
			<file href="assets/8/6b8e4b8b97b14a7b91a7490942763b38.png"/>
			<file href="assets/8/2b01bf707fb71582bfc5352e8e4b112a.jpg"/>
			<file href="assets/8/119ef0ecc903c9256399d3d1c84ee9f7.png"/>
			<file href="assets/8/df1834c537e43ef6cc33610989a2602f.png"/>
			<file href="assets/8/ee6c4cd686c883f28ca46e393c77bf4c.jpg"/>
			<file href="assets/8/ef280b8484489dee4af001c937ede34f.jpg"/>
			<file href="assets/8/978ed6c374f70230483c0693eb86e270.png"/>
			<file href="assets/8/055d11fa52b4980498462ded57eaa696.png"/>
			<file href="assets/8/3feeab305cb24d1d39244733c1919f98.jpg"/>
			<file href="assets/8/e06beb963481315a7a9cb44103364b41.jpg"/>
			<file href="assets/8/f6b8992f10c82b096cdfb39f18c5fd30.jpg"/>
			<file href="assets/8/0bffc148f0b30d8f9cc8066c31665afe.png"/>
			<file href="assets/8/ababef73bf98e95de2fb7f24bb21055b.jpg"/>
			<file href="assets/8/9c8ca276c5739d8d0f6b702500441544.jpg"/>
			<file href="assets/8/c3fb1a2ad75bc532b5f2253e5b327b1e.png"/>
			<file href="assets/8/11bed2d65ed11b1adb1412d6e0bc06e2.jpg"/>
			<file href="assets/8/7b2d1654f7852864f226b61fe0c5ec01.png"/>
			<file href="assets/8/041cba3801448838626b3f09471f9c99.jpg"/>
			<file href="assets/8/cdbc32e65426b694d75337a9e3144118.jpg"/>
			<file href="assets/8/64b8edaecce5811d4997bc7a9635a5f1.jpg"/>
			<file href="assets/8/9ad3ca9a5ccac84432f96e715f85dedf.png"/>
			<file href="assets/8/b630a5c8ddfffbc9c16c7b467af5f72a.png"/>
			<file href="assets/8/0809678149ffba3aaebba0e1c7b10116.jpg"/>
			<file href="assets/8/951522c0a5ab45c17e67a0cd6eb1e453.jpg"/>
			<file href="assets/8/790f8356685299bdc31c1cd115c4b10a.jpg"/>
			<file href="assets/8/680d0ca68bdb9bb9e26a9c26dc3b943d.jpg"/>
			<file href="assets/8/b5f78909ae4f64a6ac7bf634432c4ecc.jpg"/>
			<file href="assets/8/a6e652ad33ef19eb977e954ad44bbbd1.jpg"/>
			<file href="assets/8/a1c6d33bd819ed65f5d9297e28824ab0.jpg"/>
			<file href="assets/8/ceb446396dc6d4a59afe6837c9d4bd9f.jpg"/>
			<file href="assets/8/5065ecbe4440d07f5e6a347299891f49.jpg"/>
			<file href="assets/8/3af7464972dfc37a20ce02196edd9c3f.png"/>
			<file href="assets/8/ae7567e2f09328ae07198f1073d42fc8.jpg"/>
			<file href="assets/8/ee2d01314ac13da3877d36a301127f99.jpg"/>
			<file href="assets/8/721770765b4bb1842eb203f8c3f9d573.jpg"/>
			<file href="assets/8/5a3608a833bd963a2cb2e6c936a6608f.jpg"/>
			<file href="assets/8/ea3d5a8e59db7a26c6fdc0179fec88fb.jpg"/>
			<file href="assets/8/97da71a7b0c2704f96f233c50788664c.png"/>
			<file href="assets/8/0c6d9724b5f7ebaadd1cd29794e91111.png"/>
			<file href="assets/8/5bdddd2d86fce1da38c12931a1cabe95.png"/>
			<file href="assets/8/8cc98190bb698e1266cac0cfa61cbbbd.jpg"/>
			<file href="assets/8/a86cde4554df25df9191ecdc5f77a963.jpg"/>
			<file href="assets/8/209db5600e98aebc9c09a63c8310aa01.jpg"/>
			<file href="assets/8/0c720d71b9366d87efccc7b8ec76c115.jpg"/>
			<file href="assets/3/d3d0fc09680c6d0a8eb06579437c4981.jpg"/>
			<file href="assets/3/41e86102b5f0bae9e406382f753d1457.png"/>
			<file href="assets/3/757a7a06a348037f6bb1b68cdb080b30.png"/>
			<file href="assets/2/0b7b0a4887e3f705987cd235a4566921.jpg"/>
			<file href="assets/2/2140112114e6fd84bc44ad1d92855030.jpeg"/>
			<file href="assets/2/1f977421a99d5e64d4e4a407bfa18ff5.jpg"/>
			<file href="assets/2/d093375c2c0c17824879d979c84cada4.eot"/>
			<file href="assets/2/f6a82cc940e2a4db1d8b178764f55f8b.eot"/>
			<file href="assets/2/bdbfd04f0ab1a469c565912b9d019a6c.jpg"/>
			<file href="assets/2/009ead47c39781444f8dc87b652efc05.png"/>
			<file href="assets/2/77d2b857bf7b00647ff79b0ac4c7a597.woff"/>
			<file href="assets/2/85b3bb325666eca5fe04f1a6335d2948.jpg"/>
			<file href="assets/2/26dea78d7b4349638c7e9e9529cd82d5.jpg"/>
			<file href="assets/7/838703a217f1a68b03d5657f48c46b12.png"/>
			<file href="assets/7/e49997b8bd705c06fa67fb1e93a69bec.jpg"/>
			<file href="assets/7/239c002af32ec122c111886fd1d6e7e7.jpg"/>
			<file href="assets/7/610d34303a7c9cb768a78c5c17942011.png"/>
			<file href="assets/7/e1f073f6e605472dca9864036b14c8c9.png"/>
			<file href="assets/7/c5b50797e94a3af70bdbfa0cddde189b.jpg"/>
			<file href="assets/7/d1b92739e3b7941d1300a4d2e7719fdd.png"/>
			<file href="assets/7/8d9354ecbc4d80ad9f44841b87be1e83.jpg"/>
			<file href="assets/7/ef88a2a7d7cd7dba0a0abc60f1e67f48.jpg"/>
			<file href="assets/7/dbe23fce45c06b119953e12fe2279a40.png"/>
			<file href="assets/7/f82fc01df363239e2cb3e7f9262fca28.png"/>
			<file href="assets/7/03d091e520404761c054ac06945c37ce.jpg"/>
			<file href="assets/7/6de8efb344d9699e4722881dc35bc599.png"/>
			<file href="assets/7/c47f4064c9fdebfefc23a16c7ff2dddb.jpg"/>
			<file href="assets/7/546f759ef9d2081d40dd2bad7a9efa3d.jpg"/>
			<file href="assets/7/d8dd65a41748de97b2b9b9c6474c954d.jpg"/>
			<file href="assets/7/7d517040a99a84642064eaea8408b50b.png"/>
			<file href="assets/7/5b8950fc81c96502cbcf295200fdac81.png"/>
			<file href="assets/7/122ce7975dc6f3e78f59ee3a1bb8e6be.png"/>
			<file href="assets/7/47f7c87488842099628f5d6344c3c82c.jpg"/>
			<file href="assets/7/def8566cfc4191aaf00caa9ddcbd87c3.jpg"/>
			<file href="assets/7/82a274f7e727f68a521435fcb1165b5d.png"/>
			<file href="assets/7/5e5e755fec0731c61fce7d44beabdb14.jpg"/>
			<file href="assets/7/69718f5166600225d1fcf91389074b7a.png"/>
			<file href="assets/7/0e9bba471d3fc3c477cd2170a7983d6f.png"/>
			<file href="assets/7/c9757f683472321bc62b6b49c4ad5684.png"/>
			<file href="assets/7/35ed1ac44c526e7ce4b06156a9f8fb03.png"/>
			<file href="assets/7/aa29ed3e53ae845b3be1c2cd6a250ca7.png"/>
			<file href="assets/7/064813a27f83ebb5a572053a85e7b2cc.jpg"/>
			<file href="assets/7/1541870a7137d00b833d26fac7ed8d41.png"/>
			<file href="assets/7/66adefeb84541d594bcb8dcc3028b316.png"/>
			<file href="assets/7/86a32610b7a0db08ba7044c5b0778b1d.jpg"/>
			<file href="assets/7/98c7adfec9bf0018c96bf8a82a7b12ff.png"/>
			<file href="assets/7/8b712d45784efd446bd2f34d88c2d919.jpg"/>
			<file href="assets/7/556d5c30b9173a0fdba52dfe7de17554.jpg"/>
			<file href="assets/7/6bced1b19b50fb0a027f354307afc726.png"/>
			<file href="assets/7/faa4255df4172944837f794dc82a7dca.png"/>
			<file href="assets/7/72c1147b50e555120e6de15a8073e88f.jpg"/>
			<file href="assets/7/b3fd52779f291050158af56f425af2b4.png"/>
			<file href="assets/7/e53eb0a5fadb48392e9bdd2abe9b8365.jpg"/>
			<file href="assets/7/a38160f9cbd054f28d27509c1c6f8699.jpg"/>
			<file href="assets/7/fd7d0c7b0b907aaf205ee79d8a11fdd2.png"/>
			<file href="assets/7/7dc5c92b504fd2742f7d04919b370527.png"/>
			<file href="assets/7/9e82e008548de5a1ad190a74876194af.png"/>
			<file href="assets/7/8720bad30714ffb0729d8102e4e6814c.jpg"/>
			<file href="assets/7/4f29c198cafc02023f23b67172754df8.jpg"/>
			<file href="assets/7/73afcb4e60f5705e82d82692c10b9a39.jpg"/>
			<file href="assets/7/f37a8c99c67de92e5cf56ccd34dcb70d.jpg"/>
			<file href="assets/7/202f7d2a2755c31aaeba58f01e42332c.png"/>
			<file href="assets/7/93c663b9e75846d87e973c5c92e9283d.png"/>
			<file href="assets/1/5f23b43bf7dd7da2eb89f2b55683e62b.png"/>
			<file href="assets/58a42f9b85704.js"/>
			<file href="assets/58a42f9b85704.css"/>
			<file href="assets/6/bda6a0ae345f656db2226c7902fc372e.png"/>
			<file href="assets/6/4e2268b8c117bd6758295360a3187a84.png"/>
			<file href="login.html"/>
			<file href="launch.html"/>
			<file href="vendor/material/icomoon.svg"/>
			<file href="vendor/material/icomoon.eot"/>
			<file href="vendor/material/icomoon.ttf"/>
			<file href="vendor/material/icomoon.woff"/>
			<file href="vendor/jquery.xdr.js"/>
			<file href="vendor/fontawesome/icomoon.svg"/>
			<file href="vendor/fontawesome/icomoon.eot"/>
			<file href="vendor/fontawesome/icomoon.ttf"/>
			<file href="vendor/fontawesome/icomoon.woff"/>
			<file href="vendor/typicon/icomoon.svg"/>
			<file href="vendor/typicon/icomoon.eot"/>
			<file href="vendor/typicon/icomoon.ttf"/>
			<file href="vendor/typicon/icomoon.woff"/>
			<file href="vendor/elucidat-v2.0.min.css"/>
			<file href="vendor/modernizr-2.6.2.min.js"/>
			<file href="vendor/bootstrap/fontawesome-webfont.svg"/>
			<file href="vendor/bootstrap/fontawesome-webfont.ttf"/>
			<file href="vendor/bootstrap/glyphicons-halflings-white.png"/>
			<file href="vendor/bootstrap/fontawesome-webfont.woff2"/>
			<file href="vendor/bootstrap/fontawesome-webfont.woff"/>
			<file href="vendor/bootstrap/glyphicons-halflings.png"/>
			<file href="vendor/bootstrap/fontawesome-webfont.eot"/>
			<file href="vendor/mediaelement/bigplay.png"/>
			<file href="vendor/mediaelement/loading.gif"/>
			<file href="vendor/mediaelement/flashmediaelement-cdn.swf"/>
			<file href="vendor/mediaelement/controls-wmp.png"/>
			<file href="vendor/mediaelement/flashmediaelement.swf"/>
			<file href="vendor/mediaelement/silverlightmediaelement.xap"/>
			<file href="vendor/mediaelement/bigplay.svg"/>
			<file href="vendor/mediaelement/background.png"/>
			<file href="vendor/mediaelement/mediaelement-and-player.min.js"/>
			<file href="vendor/mediaelement/controls.svg"/>
			<file href="vendor/mediaelement/controls.png"/>
			<file href="vendor/mediaelement/controls-wmp-bg.png"/>
			<file href="vendor/mediaelement/controls-ted.png"/>
			<file href="vendor/mediaelement/flashmediaelement-cdn-2.22.0.swf"/>
			<file href="vendor/elucidat-v3.2.min.js"/>
		</resource>
	</resources>
</manifest>
